integromat_wrapper/__init__.py
integromat_wrapper/deploy.py
integromat_wrapper/integromat.py
integromat_wrapper-0.1.4.dist-info/entry_points.txt
integromat_wrapper-0.1.4.dist-info/LICENSE
integromat_wrapper-0.1.4.dist-info/WHEEL
integromat_wrapper-0.1.4.dist-info/METADATA
integromat_wrapper-0.1.4.dist-info/RECORD
