Metadata-Version: 2.1
Name: integromat-wrapper
Version: 0.1.4
Summary: 
Author: Skyler Lewis
Author-email: skyler@hivewire.co
Requires-Python: >=3.8,<4.0
Classifier: Programming Language :: Python :: 3
Classifier: Programming Language :: Python :: 3.8
Classifier: Programming Language :: Python :: 3.9
Requires-Dist: click (>=8.0.1,<9.0.0)
Requires-Dist: httpx (>=0.19.0,<0.20.0)
Requires-Dist: taskipy (>=1.8.2,<2.0.0)
